nxpydocs/__init__.py
nxpydocs/csv.j2
nxpydocs/datatable_footer.j2
nxpydocs/datatable_header.j2
nxpydocs/html.j2
nxpydocs/md.j2
nxpydocs/mindmap.j2
nxpydocs/nxpydocs.py
nxpydocs/script.py
nxpydocs-1.0.12.dist-info/entry_points.txt
nxpydocs-1.0.12.dist-info/LICENSE
nxpydocs-1.0.12.dist-info/WHEEL
nxpydocs-1.0.12.dist-info/METADATA
nxpydocs-1.0.12.dist-info/RECORD
