Metadata-Version: 2.1
Name: nxpydocs
Version: 1.0.12
Summary: Automated Business Ready Documents from the NX-OS Guestshell
Author: John Capobianco
Author-email: ptcapo@gmail.com
Requires-Python: >=2.7,<3.0
Classifier: Programming Language :: Python :: 2
Classifier: Programming Language :: Python :: 2.7
Requires-Dist: Jinja2 (==2.11.3)
Requires-Dist: PyYAML (>=5.4,<6.0)
Requires-Dist: click (==7.1.2)
Requires-Dist: furl (>=2.1.3,<3.0.0)
Requires-Dist: pathlib (>=1.0.1,<2.0.0)
